Metadata-Version: 1.1
Name: featuritis
Version: 0.1
Summary: feature tracking: know what features your deployed software has
Home-page: https://github.com/f0rk/featuritis
Author: Ryan P. Kelly
Author-email: ryan@ryankelly.us
License: UNKNOWN
Platform: UNKNOWN
Classifier: Development Status :: 3 - Alpha
Classifier: Environment :: Console
Classifier: Intended Audience :: Developers
Classifier: Intended Audience :: System Administrators
Classifier: License :: OSI Approved :: MIT License
Classifier: Operating System :: MacOS :: MacOS X
Classifier: Operating System :: POSIX
Classifier: Programming Language :: Python :: 3
Classifier: Topic :: Software Development
